projectname_pycore-0.1.1.dist-info/METADATA
projectname_pycore-0.1.1.dist-info/WHEEL
projectname_pycore-0.1.1.dist-info/entry_points.txt
pycore/__init__.py
pycore/pycore.cp311-win_amd64.pyd
projectname_pycore-0.1.1.dist-info/RECORD
