Metadata-Version: 2.4
Name: projectname-pycore
Version: 0.1.1
Requires-Dist: smooth-criminal>=0.8.0
Summary: Proyecto ejemplo PyCore con núcleo Rust y API Python
Author: Adolfo González Hernández
Requires-Python: >=3.10
